<spirit:component xmlns:actel-cc="http://www.actel.com/XMLSchema/CoreConsole" xmlns:spirit="http://www.spiritconsortium.org/XMLSchema/SPIRIT/1.1" xmlns:xsi="http://www.w3.org/2001/XMLSchema-instance" xsi:schemaLocation="http://www.spiritconsortium.org/XMLSchema/SPIRIT/1.1 http://www.spiritconsortium.org/XMLSchema/SPIRIT/1.1/component.xsd">
  <spirit:vendor>Actel</spirit:vendor>
  <spirit:library>SmartFusion2MSS</spirit:library>
  <spirit:name>MSS_SECURITY</spirit:name>
  <spirit:version>1.0.100</spirit:version>
  <spirit:busInterfaces>
  </spirit:busInterfaces>
  <spirit:memoryMaps>
  </spirit:memoryMaps>
  <spirit:hwModel>
    <spirit:views>
      <spirit:view>
        <spirit:name>Generator</spirit:name>
        <spirit:envIdentifier></spirit:envIdentifier>
        <spirit:language></spirit:language>
        <spirit:vendorExtensions>
          <actel-cc:fsInclusionRules></actel-cc:fsInclusionRules></spirit:vendorExtensions>
      </spirit:view>
    </spirit:views>
    <spirit:signals>
    </spirit:signals>
    <spirit:hwParameters>
    </spirit:hwParameters>
  <spirit:vendorExtensions>
    <actel-cc:variantParameters>
      <actel-cc:variantParameter spirit:id="FAMILY" spirit:name="FAMILY" spirit:prompt="FPGA Family:" spirit:dataType="int" actel-cc:choiceRef="Choice_FamilyValue" spirit:choiceStyle="combo" spirit:configGroups="globalConfig" spirit:resolve="user">19</actel-cc:variantParameter>
      <actel-cc:variantParameter spirit:id="MM0_1_2_MS0_ALLOWED_R" spirit:name="MM0_1_2_MS0_ALLOWED_R" spirit:prompt="Read access to slave eSRAM0" actel-cc:choiceRef="" spirit:dataType="boolean" spirit:configGroups="2Cols:Masters 0, 1 and 2 read/write access to slaves" spirit:resolve="user">1</actel-cc:variantParameter>
      <actel-cc:variantParameter spirit:id="MM0_1_2_MS0_ALLOWED_W" spirit:name="MM0_1_2_MS0_ALLOWED_W" spirit:prompt="Write access to slave eSRAM0" actel-cc:choiceRef="" spirit:dataType="boolean" spirit:configGroups="2Cols:Masters 0, 1 and 2 read/write access to slaves" spirit:resolve="user">1</actel-cc:variantParameter>
      <actel-cc:variantParameter spirit:id="MM0_1_2_MS1_ALLOWED_R" spirit:name="MM0_1_2_MS1_ALLOWED_R" spirit:prompt="Read access to slave eSRAM1" actel-cc:choiceRef="" spirit:dataType="boolean" spirit:configGroups="2Cols:Masters 0, 1 and 2 read/write access to slaves" spirit:resolve="user">1</actel-cc:variantParameter>
      <actel-cc:variantParameter spirit:id="MM0_1_2_MS1_ALLOWED_W" spirit:name="MM0_1_2_MS1_ALLOWED_W" spirit:prompt="Write access to slave eSRAM1" actel-cc:choiceRef="" spirit:dataType="boolean" spirit:configGroups="2Cols:Masters 0, 1 and 2 read/write access to slaves" spirit:resolve="user">1</actel-cc:variantParameter>
      <actel-cc:variantParameter spirit:id="MM0_1_2_MS2_ALLOWED_R" spirit:name="MM0_1_2_MS2_ALLOWED_R" spirit:prompt="Read access to slave eNVM0" actel-cc:choiceRef="" spirit:dataType="boolean" spirit:configGroups="2Cols:Masters 0, 1 and 2 read/write access to slaves" spirit:resolve="user">1</actel-cc:variantParameter>
      <actel-cc:variantParameter spirit:id="MM0_1_2_MS2_ALLOWED_W" spirit:name="MM0_1_2_MS2_ALLOWED_W" spirit:prompt="Write access to slave eNVM0" actel-cc:choiceRef="" spirit:dataType="boolean" spirit:configGroups="2Cols:Masters 0, 1 and 2 read/write access to slaves" spirit:resolve="user">1</actel-cc:variantParameter>
      <actel-cc:variantParameter spirit:id="MM0_1_2_MS3_ALLOWED_R" spirit:name="MM0_1_2_MS3_ALLOWED_R" spirit:prompt="Read access to slave eNVM1" actel-cc:choiceRef="" spirit:dataType="boolean" spirit:configGroups="2Cols:Masters 0, 1 and 2 read/write access to slaves" spirit:resolve="user">1</actel-cc:variantParameter>
      <actel-cc:variantParameter spirit:id="MM0_1_2_MS3_ALLOWED_W" spirit:name="MM0_1_2_MS3_ALLOWED_W" spirit:prompt="Write access to slave eNVM1" actel-cc:choiceRef="" spirit:dataType="boolean" spirit:configGroups="2Cols:Masters 0, 1 and 2 read/write access to slaves" spirit:resolve="user">1</actel-cc:variantParameter>
      <actel-cc:variantParameter spirit:id="MM0_1_2_MS6_ALLOWED_R" spirit:name="MM0_1_2_MS6_ALLOWED_R" spirit:prompt="Read access to slave DDR Bridge" actel-cc:choiceRef="" spirit:dataType="boolean" spirit:configGroups="2Cols:Masters 0, 1 and 2 read/write access to slaves" spirit:resolve="user">1</actel-cc:variantParameter>
      <actel-cc:variantParameter spirit:id="MM0_1_2_MS6_ALLOWED_W" spirit:name="MM0_1_2_MS6_ALLOWED_W" spirit:prompt="Write access to slave DDR Bridge" actel-cc:choiceRef="" spirit:dataType="boolean" spirit:configGroups="2Cols:Masters 0, 1 and 2 read/write access to slaves" spirit:resolve="user">1</actel-cc:variantParameter>
      <actel-cc:variantParameter spirit:id="MM4_5_FIC64_MS0_ALLOWED_R" spirit:name="MM4_5_FIC64_MS0_ALLOWED_R" spirit:prompt="Read access to slave eSRAM0" actel-cc:choiceRef="" spirit:dataType="boolean" spirit:configGroups="2Cols:Masters 4, 5 and FIC64 read/write access to slaves" spirit:resolve="user">1</actel-cc:variantParameter>
      <actel-cc:variantParameter spirit:id="MM4_5_FIC64_MS0_ALLOWED_W" spirit:name="MM4_5_FIC64_MS0_ALLOWED_W" spirit:prompt="Write access to slave eSRAM0" actel-cc:choiceRef="" spirit:dataType="boolean" spirit:configGroups="2Cols:Masters 4, 5 and FIC64 read/write access to slaves" spirit:resolve="user">1</actel-cc:variantParameter>
      <actel-cc:variantParameter spirit:id="MM4_5_FIC64_MS1_ALLOWED_R" spirit:name="MM4_5_FIC64_MS1_ALLOWED_R" spirit:prompt="Read access to slave eSRAM1" actel-cc:choiceRef="" spirit:dataType="boolean" spirit:configGroups="2Cols:Masters 4, 5 and FIC64 read/write access to slaves" spirit:resolve="user">1</actel-cc:variantParameter>
      <actel-cc:variantParameter spirit:id="MM4_5_FIC64_MS1_ALLOWED_W" spirit:name="MM4_5_FIC64_MS1_ALLOWED_W" spirit:prompt="Write access to slave eSRAM1" actel-cc:choiceRef="" spirit:dataType="boolean" spirit:configGroups="2Cols:Masters 4, 5 and FIC64 read/write access to slaves" spirit:resolve="user">1</actel-cc:variantParameter>
      <actel-cc:variantParameter spirit:id="MM4_5_FIC64_MS2_ALLOWED_R" spirit:name="MM4_5_FIC64_MS2_ALLOWED_R" spirit:prompt="Read access to slave eNVM0" actel-cc:choiceRef="" spirit:dataType="boolean" spirit:configGroups="2Cols:Masters 4, 5 and FIC64 read/write access to slaves" spirit:resolve="user">1</actel-cc:variantParameter>
      <actel-cc:variantParameter spirit:id="MM4_5_FIC64_MS2_ALLOWED_W" spirit:name="MM4_5_FIC64_MS2_ALLOWED_W" spirit:prompt="Write access to slave eNVM0" actel-cc:choiceRef="" spirit:dataType="boolean" spirit:configGroups="2Cols:Masters 4, 5 and FIC64 read/write access to slaves" spirit:resolve="user">1</actel-cc:variantParameter>
      <actel-cc:variantParameter spirit:id="MM4_5_FIC64_MS3_ALLOWED_R" spirit:name="MM4_5_FIC64_MS3_ALLOWED_R" spirit:prompt="Read access to slave eNVM1" actel-cc:choiceRef="" spirit:dataType="boolean" spirit:configGroups="2Cols:Masters 4, 5 and FIC64 read/write access to slaves" spirit:resolve="user">1</actel-cc:variantParameter>
      <actel-cc:variantParameter spirit:id="MM4_5_FIC64_MS3_ALLOWED_W" spirit:name="MM4_5_FIC64_MS3_ALLOWED_W" spirit:prompt="Write access to slave eNVM1" actel-cc:choiceRef="" spirit:dataType="boolean" spirit:configGroups="2Cols:Masters 4, 5 and FIC64 read/write access to slaves" spirit:resolve="user">1</actel-cc:variantParameter>
      <actel-cc:variantParameter spirit:id="MM4_5_FIC64_MS6_ALLOWED_R" spirit:name="MM4_5_FIC64_MS6_ALLOWED_R" spirit:prompt="Read access to slave DDR Bridge" actel-cc:choiceRef="" spirit:dataType="boolean" spirit:configGroups="2Cols:Masters 4, 5 and FIC64 read/write access to slaves" spirit:resolve="user">1</actel-cc:variantParameter>
      <actel-cc:variantParameter spirit:id="MM4_5_FIC64_MS6_ALLOWED_W" spirit:name="MM4_5_FIC64_MS6_ALLOWED_W" spirit:prompt="Write access to slave DDR Bridge" actel-cc:choiceRef="" spirit:dataType="boolean" spirit:configGroups="2Cols:Masters 4, 5 and FIC64 read/write access to slaves" spirit:resolve="user">1</actel-cc:variantParameter>
      <actel-cc:variantParameter spirit:id="MM3_6_7_8_MS0_ALLOWED_R" spirit:name="MM3_6_7_8_MS0_ALLOWED_R" spirit:prompt="Read access to slave eSRAM0" actel-cc:choiceRef="" spirit:dataType="boolean" spirit:configGroups="2Cols:Masters 3, 6, 7 and 8 read/write access to slaves" spirit:resolve="user">1</actel-cc:variantParameter>
      <actel-cc:variantParameter spirit:id="MM3_6_7_8_MS0_ALLOWED_W" spirit:name="MM3_6_7_8_MS0_ALLOWED_W" spirit:prompt="Write access to slave eSRAM0" actel-cc:choiceRef="" spirit:dataType="boolean" spirit:configGroups="2Cols:Masters 3, 6, 7 and 8 read/write access to slaves" spirit:resolve="user">1</actel-cc:variantParameter>
      <actel-cc:variantParameter spirit:id="MM3_6_7_8_MS1_ALLOWED_R" spirit:name="MM3_6_7_8_MS1_ALLOWED_R" spirit:prompt="Read access to slave eSRAM1" actel-cc:choiceRef="" spirit:dataType="boolean" spirit:configGroups="2Cols:Masters 3, 6, 7 and 8 read/write access to slaves" spirit:resolve="user">1</actel-cc:variantParameter>
      <actel-cc:variantParameter spirit:id="MM3_6_7_8_MS1_ALLOWED_W" spirit:name="MM3_6_7_8_MS1_ALLOWED_W" spirit:prompt="Write access to slave eSRAM1" actel-cc:choiceRef="" spirit:dataType="boolean" spirit:configGroups="2Cols:Masters 3, 6, 7 and 8 read/write access to slaves" spirit:resolve="user">1</actel-cc:variantParameter>
      <actel-cc:variantParameter spirit:id="MM3_6_7_8_MS2_ALLOWED_R" spirit:name="MM3_6_7_8_MS2_ALLOWED_R" spirit:prompt="Read access to slave eNVM0" actel-cc:choiceRef="" spirit:dataType="boolean" spirit:configGroups="2Cols:Masters 3, 6, 7 and 8 read/write access to slaves" spirit:resolve="user">1</actel-cc:variantParameter>
      <actel-cc:variantParameter spirit:id="MM3_6_7_8_MS2_ALLOWED_W" spirit:name="MM3_6_7_8_MS2_ALLOWED_W" spirit:prompt="Write access to slave eNVM0" actel-cc:choiceRef="" spirit:dataType="boolean" spirit:configGroups="2Cols:Masters 3, 6, 7 and 8 read/write access to slaves" spirit:resolve="user">1</actel-cc:variantParameter>
      <actel-cc:variantParameter spirit:id="MM3_6_7_8_MS3_ALLOWED_R" spirit:name="MM3_6_7_8_MS3_ALLOWED_R" spirit:prompt="Read access to slave eNVM1" actel-cc:choiceRef="" spirit:dataType="boolean" spirit:configGroups="2Cols:Masters 3, 6, 7 and 8 read/write access to slaves" spirit:resolve="user">1</actel-cc:variantParameter>
      <actel-cc:variantParameter spirit:id="MM3_6_7_8_MS3_ALLOWED_W" spirit:name="MM3_6_7_8_MS3_ALLOWED_W" spirit:prompt="Write access to slave eNVM1" actel-cc:choiceRef="" spirit:dataType="boolean" spirit:configGroups="2Cols:Masters 3, 6, 7 and 8 read/write access to slaves" spirit:resolve="user">1</actel-cc:variantParameter>
      <actel-cc:variantParameter spirit:id="MM3_6_7_8_MS6_ALLOWED_R" spirit:name="MM3_6_7_8_MS6_ALLOWED_R" spirit:prompt="Read access to slave DDR Bridge" actel-cc:choiceRef="" spirit:dataType="boolean" spirit:configGroups="2Cols:Masters 3, 6, 7 and 8 read/write access to slaves" spirit:resolve="user">1</actel-cc:variantParameter>
      <actel-cc:variantParameter spirit:id="MM3_6_7_8_MS6_ALLOWED_W" spirit:name="MM3_6_7_8_MS6_ALLOWED_W" spirit:prompt="Write access to slave DDR Bridge" actel-cc:choiceRef="" spirit:dataType="boolean" spirit:configGroups="2Cols:Masters 3, 6, 7 and 8 read/write access to slaves" spirit:resolve="user">1</actel-cc:variantParameter>
      <actel-cc:variantParameter spirit:id="MM9_MS0_ALLOWED_R" spirit:name="MM9_MS0_ALLOWED_R" spirit:prompt="Read access to slave eSRAM0" actel-cc:choiceRef="" spirit:dataType="boolean" spirit:configGroups="2Cols:Masters 9 read/write access to slaves" spirit:resolve="user">1</actel-cc:variantParameter>
      <actel-cc:variantParameter spirit:id="MM9_MS0_ALLOWED_W" spirit:name="MM9_MS0_ALLOWED_W" spirit:prompt="Write access to slave eSRAM0" actel-cc:choiceRef="" spirit:dataType="boolean" spirit:configGroups="2Cols:Masters 9 read/write access to slaves" spirit:resolve="user">1</actel-cc:variantParameter>
      <actel-cc:variantParameter spirit:id="MM9_MS1_ALLOWED_R" spirit:name="MM9_MS1_ALLOWED_R" spirit:prompt="Read access to slave eSRAM1" actel-cc:choiceRef="" spirit:dataType="boolean" spirit:configGroups="2Cols:Masters 9 read/write access to slaves" spirit:resolve="user">1</actel-cc:variantParameter>
      <actel-cc:variantParameter spirit:id="MM9_MS1_ALLOWED_W" spirit:name="MM9_MS1_ALLOWED_W" spirit:prompt="Write access to slave eSRAM1" actel-cc:choiceRef="" spirit:dataType="boolean" spirit:configGroups="2Cols:Masters 9 read/write access to slaves" spirit:resolve="user">1</actel-cc:variantParameter>
      <actel-cc:variantParameter spirit:id="MM9_MS2_ALLOWED_R" spirit:name="MM9_MS2_ALLOWED_R" spirit:prompt="Read access to slave eNVM0" actel-cc:choiceRef="" spirit:dataType="boolean" spirit:configGroups="2Cols:Masters 9 read/write access to slaves" spirit:resolve="user">1</actel-cc:variantParameter>
      <actel-cc:variantParameter spirit:id="MM9_MS2_ALLOWED_W" spirit:name="MM9_MS2_ALLOWED_W" spirit:prompt="Write access to slave eNVM0" actel-cc:choiceRef="" spirit:dataType="boolean" spirit:configGroups="2Cols:Masters 9 read/write access to slaves" spirit:resolve="user">1</actel-cc:variantParameter>
      <actel-cc:variantParameter spirit:id="MM9_MS3_ALLOWED_R" spirit:name="MM9_MS3_ALLOWED_R" spirit:prompt="Read access to slave eNVM1" actel-cc:choiceRef="" spirit:dataType="boolean" spirit:configGroups="2Cols:Masters 9 read/write access to slaves" spirit:resolve="user">1</actel-cc:variantParameter>
      <actel-cc:variantParameter spirit:id="MM9_MS3_ALLOWED_W" spirit:name="MM9_MS3_ALLOWED_W" spirit:prompt="Write access to slave eNVM1" actel-cc:choiceRef="" spirit:dataType="boolean" spirit:configGroups="2Cols:Masters 9 read/write access to slaves" spirit:resolve="user">1</actel-cc:variantParameter>
      <actel-cc:variantParameter spirit:id="MM9_MS6_ALLOWED_R" spirit:name="MM9_MS6_ALLOWED_R" spirit:prompt="Read access to slave DDR Bridge" actel-cc:choiceRef="" spirit:dataType="boolean" spirit:configGroups="2Cols:Masters 9 read/write access to slaves" spirit:resolve="user">1</actel-cc:variantParameter>
      <actel-cc:variantParameter spirit:id="MM9_MS6_ALLOWED_W" spirit:name="MM9_MS6_ALLOWED_W" spirit:prompt="Write access to slave DDR Bridge" actel-cc:choiceRef="" spirit:dataType="boolean" spirit:configGroups="2Cols:Masters 9 read/write access to slaves" spirit:resolve="user">1</actel-cc:variantParameter>
      <actel-cc:variantParameter spirit:id="FABRIC_MEMPROT_IS_USED" spirit:name="FABRIC_MEMPROT_IS_USED" spirit:prompt="Restrict Memory Access" actel-cc:choiceRef="" spirit:dataType="boolean" spirit:configGroups="Fabric Master Memory Access" spirit:resolve="user">0</actel-cc:variantParameter>
      <actel-cc:variantParameter spirit:id="FABRIC_MEMPROT_REGION_SIZE" spirit:name="FABRIC_MEMPROT_REGION_SIZE" spirit:prompt="Restricted Memory Region Size" spirit:dataType="string" actel-cc:choiceRef="FABRIC_MEMPROT_REGION_SIZE_CHOICES" spirit:configGroups="Fabric Master Memory Access" spirit:resolve="user">8MB</actel-cc:variantParameter>
      <actel-cc:variantParameter spirit:id="FABRIC_MEMPROT_BASE_ADDRESS" spirit:name="FABRIC_MEMPROT_BASE_ADDRESS" spirit:prompt="Restricted Memory Base Address" actel-cc:choiceRef="" spirit:dataType="string" spirit:configGroups="Fabric Master Memory Access" spirit:resolve="user">0x00000000</actel-cc:variantParameter>
      <actel-cc:variantParameter spirit:id="NVM0_LOWER_M3ACCESS" spirit:name="NVM0_LOWER_M3ACCESS" spirit:prompt="Allow M3 to access the lower protection region of ENVM0" actel-cc:choiceRef="" spirit:dataType="boolean" spirit:configGroups="ENVM0 Protection" spirit:resolve="user">1</actel-cc:variantParameter>
      <actel-cc:variantParameter spirit:id="NVM0_LOWER_FABRIC_ACCESS" spirit:name="NVM0_LOWER_FABRIC_ACCESS" spirit:prompt="Allow Fabric masters to access the lower protection region of ENVM0" actel-cc:choiceRef="" spirit:dataType="boolean" spirit:configGroups="ENVM0 Protection" spirit:resolve="user">1</actel-cc:variantParameter>
      <actel-cc:variantParameter spirit:id="NVM0_LOWER_OTHERS_ACCESS" spirit:name="NVM0_LOWER_OTHERS_ACCESS" spirit:prompt="Allow other masters to access the lower protection region of ENVM0" actel-cc:choiceRef="" spirit:dataType="boolean" spirit:configGroups="ENVM0 Protection" spirit:resolve="user">1</actel-cc:variantParameter>
      <actel-cc:variantParameter spirit:id="NVM0_LOWER_ALLOWED" spirit:name="NVM0_LOWER_ALLOWED" spirit:prompt="Allow write access to masters that have read access the lower protection region of ENVM0" actel-cc:choiceRef="" spirit:dataType="boolean" spirit:configGroups="ENVM0 Protection" spirit:resolve="user">1</actel-cc:variantParameter>
      <actel-cc:variantParameter spirit:id="NVM0_UPPER_M3ACCESS" spirit:name="NVM0_UPPER_M3ACCESS" spirit:prompt="Allow M3 to access the power protection region of ENVM0" actel-cc:choiceRef="" spirit:dataType="boolean" spirit:configGroups="ENVM0 Protection" spirit:resolve="user">1</actel-cc:variantParameter>
      <actel-cc:variantParameter spirit:id="NVM0_UPPER_FABRIC_ACCESS" spirit:name="NVM0_UPPER_FABRIC_ACCESS" spirit:prompt="Allow Fabric masters to access the power protection region of ENVM0" actel-cc:choiceRef="" spirit:dataType="boolean" spirit:configGroups="ENVM0 Protection" spirit:resolve="user">1</actel-cc:variantParameter>
      <actel-cc:variantParameter spirit:id="NVM0_UPPER_OTHERS_ACCESS" spirit:name="NVM0_UPPER_OTHERS_ACCESS" spirit:prompt="Allow other masters to access the power protection region of ENVM0" actel-cc:choiceRef="" spirit:dataType="boolean" spirit:configGroups="ENVM0 Protection" spirit:resolve="user">1</actel-cc:variantParameter>
      <actel-cc:variantParameter spirit:id="NVM0_UPPER_ALLOWED" spirit:name="NVM0_UPPER_ALLOWED" spirit:prompt="Allow write access to masters that have read access the power protection region of ENVM0" actel-cc:choiceRef="" spirit:dataType="boolean" spirit:configGroups="ENVM0 Protection" spirit:resolve="user">1</actel-cc:variantParameter>
      <actel-cc:variantParameter spirit:id="NVM1_LOWER_M3ACCESS" spirit:name="NVM1_LOWER_M3ACCESS" spirit:prompt="Allow M3 to access the lower protection region of ENVM1" actel-cc:choiceRef="" spirit:dataType="boolean" spirit:configGroups="ENVM1 Protection" spirit:resolve="user">1</actel-cc:variantParameter>
      <actel-cc:variantParameter spirit:id="NVM1_LOWER_FABRIC_ACCESS" spirit:name="NVM1_LOWER_FABRIC_ACCESS" spirit:prompt="Allow Fabric masters to access the lower protection region of ENVM1" actel-cc:choiceRef="" spirit:dataType="boolean" spirit:configGroups="ENVM1 Protection" spirit:resolve="user">1</actel-cc:variantParameter>
      <actel-cc:variantParameter spirit:id="NVM1_LOWER_OTHERS_ACCESS" spirit:name="NVM1_LOWER_OTHERS_ACCESS" spirit:prompt="Allow other masters to access the lower protection region of ENVM1" actel-cc:choiceRef="" spirit:dataType="boolean" spirit:configGroups="ENVM1 Protection" spirit:resolve="user">1</actel-cc:variantParameter>
      <actel-cc:variantParameter spirit:id="NVM1_LOWER_ALLOWED" spirit:name="NVM1_LOWER_ALLOWED" spirit:prompt="Allow write access to masters that have read access the lower protection region of ENVM1" actel-cc:choiceRef="" spirit:dataType="boolean" spirit:configGroups="ENVM1 Protection" spirit:resolve="user">1</actel-cc:variantParameter>
      <actel-cc:variantParameter spirit:id="NVM1_UPPER_M3ACCESS" spirit:name="NVM1_UPPER_M3ACCESS" spirit:prompt="Allow M3 to access the power protection region of ENVM1" actel-cc:choiceRef="" spirit:dataType="boolean" spirit:configGroups="ENVM1 Protection" spirit:resolve="user">1</actel-cc:variantParameter>
      <actel-cc:variantParameter spirit:id="NVM1_UPPER_FABRIC_ACCESS" spirit:name="NVM1_UPPER_FABRIC_ACCESS" spirit:prompt="Allow Fabric masters to access the power protection region of ENVM1" actel-cc:choiceRef="" spirit:dataType="boolean" spirit:configGroups="ENVM1 Protection" spirit:resolve="user">1</actel-cc:variantParameter>
      <actel-cc:variantParameter spirit:id="NVM1_UPPER_OTHERS_ACCESS" spirit:name="NVM1_UPPER_OTHERS_ACCESS" spirit:prompt="Allow other masters to access the power protection region of ENVM1" actel-cc:choiceRef="" spirit:dataType="boolean" spirit:configGroups="ENVM1 Protection" spirit:resolve="user">1</actel-cc:variantParameter>
      <actel-cc:variantParameter spirit:id="NVM1_UPPER_ALLOWED" spirit:name="NVM1_UPPER_ALLOWED" spirit:prompt="Allow write access to masters that have read access the power protection region of ENVM1" actel-cc:choiceRef="" spirit:dataType="boolean" spirit:configGroups="ENVM1 Protection" spirit:resolve="user">1</actel-cc:variantParameter>
      <actel-cc:variantParameter spirit:id="ESRAM_CONFIG_OVERRIDE" spirit:name="ESRAM_CONFIG_OVERRIDE" spirit:prompt="ESRAM_CONFIG" actel-cc:choiceRef="" spirit:dataType="boolean" spirit:configGroups="4Cols:Allow Configuration Registers Override from Masters" spirit:resolve="user">1</actel-cc:variantParameter>
      <actel-cc:variantParameter spirit:id="ESRAM_MAX_LAT_OVERRIDE" spirit:name="ESRAM_MAX_LAT_OVERRIDE" spirit:prompt="ESRAM_MAX_LAT" actel-cc:choiceRef="" spirit:dataType="boolean" spirit:configGroups="4Cols:Allow Configuration Registers Override from Masters" spirit:resolve="user">1</actel-cc:variantParameter>
      <actel-cc:variantParameter spirit:id="DDR_CONFIG_OVERRIDE" spirit:name="DDR_CONFIG_OVERRIDE" spirit:prompt="DDR_CONFIG" actel-cc:choiceRef="" spirit:dataType="boolean" spirit:configGroups="4Cols:Allow Configuration Registers Override from Masters" spirit:resolve="user">1</actel-cc:variantParameter>
      <actel-cc:variantParameter spirit:id="ENVM_CONFIG_OVERRIDE" spirit:name="ENVM_CONFIG_OVERRIDE" spirit:prompt="ENVM_CONFIG" actel-cc:choiceRef="" spirit:dataType="boolean" spirit:configGroups="4Cols:Allow Configuration Registers Override from Masters" spirit:resolve="user">1</actel-cc:variantParameter>
      <actel-cc:variantParameter spirit:id="ENVM_REMAP_BASE_OVERRIDE" spirit:name="ENVM_REMAP_BASE_OVERRIDE" spirit:prompt="ENVM_REMAP_BASE" actel-cc:choiceRef="" spirit:dataType="boolean" spirit:configGroups="4Cols:Allow Configuration Registers Override from Masters" spirit:resolve="user">1</actel-cc:variantParameter>
      <actel-cc:variantParameter spirit:id="ENVM_FAB_REMAP_OVERRIDE" spirit:name="ENVM_FAB_REMAP_OVERRIDE" spirit:prompt="ENVM_FAB_REMAP" actel-cc:choiceRef="" spirit:dataType="boolean" spirit:configGroups="4Cols:Allow Configuration Registers Override from Masters" spirit:resolve="user">1</actel-cc:variantParameter>
      <actel-cc:variantParameter spirit:id="CC_CONFIG_OVERRIDE" spirit:name="CC_CONFIG_OVERRIDE" spirit:prompt="CC_CONFIG" actel-cc:choiceRef="" spirit:dataType="boolean" spirit:configGroups="4Cols:Allow Configuration Registers Override from Masters" spirit:resolve="user">1</actel-cc:variantParameter>
      <actel-cc:variantParameter spirit:id="CC_CACHEREGION_OVERRIDE" spirit:name="CC_CACHEREGION_OVERRIDE" spirit:prompt="CC_CACHEREGION" actel-cc:choiceRef="" spirit:dataType="boolean" spirit:configGroups="4Cols:Allow Configuration Registers Override from Masters" spirit:resolve="user">1</actel-cc:variantParameter>
      <actel-cc:variantParameter spirit:id="CC_LOCKBASEADDR_OVERRIDE" spirit:name="CC_LOCKBASEADDR_OVERRIDE" spirit:prompt="CC_LOCKBASEADDR" actel-cc:choiceRef="" spirit:dataType="boolean" spirit:configGroups="4Cols:Allow Configuration Registers Override from Masters" spirit:resolve="user">1</actel-cc:variantParameter>
      <actel-cc:variantParameter spirit:id="CC_FLUSHINDX_OVERRIDE" spirit:name="CC_FLUSHINDX_OVERRIDE" spirit:prompt="CC_FLUSHINDX" actel-cc:choiceRef="" spirit:dataType="boolean" spirit:configGroups="4Cols:Allow Configuration Registers Override from Masters" spirit:resolve="user">1</actel-cc:variantParameter>
      <actel-cc:variantParameter spirit:id="DDRB_BUF_TIMER_OVERRIDE" spirit:name="DDRB_BUF_TIMER_OVERRIDE" spirit:prompt="DDRB_BUF_TIMER" actel-cc:choiceRef="" spirit:dataType="boolean" spirit:configGroups="4Cols:Allow Configuration Registers Override from Masters" spirit:resolve="user">1</actel-cc:variantParameter>
      <actel-cc:variantParameter spirit:id="DDRB_NB_ADR_OVERRIDE" spirit:name="DDRB_NB_ADR_OVERRIDE" spirit:prompt="DDRB_NB_ADR" actel-cc:choiceRef="" spirit:dataType="boolean" spirit:configGroups="4Cols:Allow Configuration Registers Override from Masters" spirit:resolve="user">1</actel-cc:variantParameter>
      <actel-cc:variantParameter spirit:id="DDRB_NB_SIZE_OVERRIDE" spirit:name="DDRB_NB_SIZE_OVERRIDE" spirit:prompt="DDRB_NB_SIZE" actel-cc:choiceRef="" spirit:dataType="boolean" spirit:configGroups="4Cols:Allow Configuration Registers Override from Masters" spirit:resolve="user">1</actel-cc:variantParameter>
      <actel-cc:variantParameter spirit:id="DDRB_CONFIG_OVERRIDE" spirit:name="DDRB_CONFIG_OVERRIDE" spirit:prompt="DDRB_CONFIG" actel-cc:choiceRef="" spirit:dataType="boolean" spirit:configGroups="4Cols:Allow Configuration Registers Override from Masters" spirit:resolve="user">1</actel-cc:variantParameter>
      <actel-cc:variantParameter spirit:id="EDAC_ENABLE_OVERRIDE" spirit:name="EDAC_ENABLE_OVERRIDE" spirit:prompt="EDAC_ENABLE" actel-cc:choiceRef="" spirit:dataType="boolean" spirit:configGroups="4Cols:Allow Configuration Registers Override from Masters" spirit:resolve="user">1</actel-cc:variantParameter>
      <actel-cc:variantParameter spirit:id="MASTER_WEIGHT_CONFIG0_OVERRIDE" spirit:name="MASTER_WEIGHT_CONFIG0_OVERRIDE" spirit:prompt="MASTER_WEIGHT_CONFIG0" actel-cc:choiceRef="" spirit:dataType="boolean" spirit:configGroups="4Cols:Allow Configuration Registers Override from Masters" spirit:resolve="user">1</actel-cc:variantParameter>
      <actel-cc:variantParameter spirit:id="MASTER_WEIGHT_CONFIG1_OVERRIDE" spirit:name="MASTER_WEIGHT_CONFIG1_OVERRIDE" spirit:prompt="MASTER_WEIGHT_CONFIG1" actel-cc:choiceRef="" spirit:dataType="boolean" spirit:configGroups="4Cols:Allow Configuration Registers Override from Masters" spirit:resolve="user">1</actel-cc:variantParameter>
      <actel-cc:variantParameter spirit:id="SOFT_INTERRUPT_OVERRIDE" spirit:name="SOFT_INTERRUPT_OVERRIDE" spirit:prompt="SOFT_INTERRUPT" actel-cc:choiceRef="" spirit:dataType="boolean" spirit:configGroups="4Cols:Allow Configuration Registers Override from Masters" spirit:resolve="user">1</actel-cc:variantParameter>
      <actel-cc:variantParameter spirit:id="M3_CONFIG_OVERRIDE" spirit:name="M3_CONFIG_OVERRIDE" spirit:prompt="M3_CONFIG" actel-cc:choiceRef="" spirit:dataType="boolean" spirit:configGroups="4Cols:Allow Configuration Registers Override from Masters" spirit:resolve="user">1</actel-cc:variantParameter>
      <actel-cc:variantParameter spirit:id="FAB_IF_OVERRIDE" spirit:name="FAB_IF_OVERRIDE" spirit:prompt="FAB_IF" actel-cc:choiceRef="" spirit:dataType="boolean" spirit:configGroups="4Cols:Allow Configuration Registers Override from Masters" spirit:resolve="user">1</actel-cc:variantParameter>
      <actel-cc:variantParameter spirit:id="LOOPBACK_CTRL_OVERRIDE" spirit:name="LOOPBACK_CTRL_OVERRIDE" spirit:prompt="LOOPBACK_CTRL" actel-cc:choiceRef="" spirit:dataType="boolean" spirit:configGroups="4Cols:Allow Configuration Registers Override from Masters" spirit:resolve="user">1</actel-cc:variantParameter>
      <actel-cc:variantParameter spirit:id="GPIO_SYSRESET_SEL_OVERRIDE" spirit:name="GPIO_SYSRESET_SEL_OVERRIDE" spirit:prompt="GPIO_SYSRESET_SEL" actel-cc:choiceRef="" spirit:dataType="boolean" spirit:configGroups="4Cols:Allow Configuration Registers Override from Masters" spirit:resolve="user">1</actel-cc:variantParameter>
      <actel-cc:variantParameter spirit:id="GPIN_SRC_SEL_OVERRIDE" spirit:name="GPIN_SRC_SEL_OVERRIDE" spirit:prompt="GPIN_SRC_SEL" actel-cc:choiceRef="" spirit:dataType="boolean" spirit:configGroups="4Cols:Allow Configuration Registers Override from Masters" spirit:resolve="user">1</actel-cc:variantParameter>
      <actel-cc:variantParameter spirit:id="MDDR_CONFIG_OVERRIDE" spirit:name="MDDR_CONFIG_OVERRIDE" spirit:prompt="MDDR_CONFIG" actel-cc:choiceRef="" spirit:dataType="boolean" spirit:configGroups="4Cols:Allow Configuration Registers Override from Masters" spirit:resolve="user">1</actel-cc:variantParameter>
      <actel-cc:variantParameter spirit:id="USB_IO_INPUT_SEL_OVERRIDE" spirit:name="USB_IO_INPUT_SEL_OVERRIDE" spirit:prompt="USB_IO_INPUT_SEL" actel-cc:choiceRef="" spirit:dataType="boolean" spirit:configGroups="4Cols:Allow Configuration Registers Override from Masters" spirit:resolve="user">1</actel-cc:variantParameter>
      <actel-cc:variantParameter spirit:id="PERIPH_CLOCK_MUX_SEL_OVERRIDE" spirit:name="PERIPH_CLOCK_MUX_SEL_OVERRIDE" spirit:prompt="PERIPH_CLOCK_MUX_SEL" actel-cc:choiceRef="" spirit:dataType="boolean" spirit:configGroups="4Cols:Allow Configuration Registers Override from Masters" spirit:resolve="user">1</actel-cc:variantParameter>
      <actel-cc:variantParameter spirit:id="WDOGCONFIG_OVERRIDE" spirit:name="WDOGCONFIG_OVERRIDE" spirit:prompt="WDOGCONFIG" actel-cc:choiceRef="" spirit:dataType="boolean" spirit:configGroups="4Cols:Allow Configuration Registers Override from Masters" spirit:resolve="user">1</actel-cc:variantParameter>
      <actel-cc:variantParameter spirit:id="MDDR_IO_CALIB_OVERRIDE" spirit:name="MDDR_IO_CALIB_OVERRIDE" spirit:prompt="MDDR_IO_CALIB" actel-cc:choiceRef="" spirit:dataType="boolean" spirit:configGroups="4Cols:Allow Configuration Registers Override from Masters" spirit:resolve="user">1</actel-cc:variantParameter>
      <actel-cc:variantParameter spirit:id="SPARE_OUT_OVERRIDE" spirit:name="SPARE_OUT_OVERRIDE" spirit:prompt="SPARE_OUT" actel-cc:choiceRef="" spirit:dataType="boolean" spirit:configGroups="4Cols:Allow Configuration Registers Override from Masters" spirit:resolve="user">1</actel-cc:variantParameter>
      <actel-cc:variantParameter spirit:id="EDAC_INT_ENABLE_OVERRIDE" spirit:name="EDAC_INT_ENABLE_OVERRIDE" spirit:prompt="EDAC_INT_ENABLE" actel-cc:choiceRef="" spirit:dataType="boolean" spirit:configGroups="4Cols:Allow Configuration Registers Override from Masters" spirit:resolve="user">1</actel-cc:variantParameter>
      <actel-cc:variantParameter spirit:id="USB_CONFIG_OVERRIDE" spirit:name="USB_CONFIG_OVERRIDE" spirit:prompt="USB_CONFIG" actel-cc:choiceRef="" spirit:dataType="boolean" spirit:configGroups="4Cols:Allow Configuration Registers Override from Masters" spirit:resolve="user">1</actel-cc:variantParameter>
      <actel-cc:variantParameter spirit:id="ESRAM_PIPELINE_CONFIG_OVERRIDE" spirit:name="ESRAM_PIPELINE_CONFIG_OVERRIDE" spirit:prompt="ESRAM_PIPELINE_CONFIG" actel-cc:choiceRef="" spirit:dataType="boolean" spirit:configGroups="4Cols:Allow Configuration Registers Override from Masters" spirit:resolve="user">1</actel-cc:variantParameter>
      <actel-cc:variantParameter spirit:id="MSS_INTERRUPT_ENABLE_OVERRIDE" spirit:name="MSS_INTERRUPT_ENABLE_OVERRIDE" spirit:prompt="MSS_INTERRUPT_ENABLE" actel-cc:choiceRef="" spirit:dataType="boolean" spirit:configGroups="4Cols:Allow Configuration Registers Override from Masters" spirit:resolve="user">1</actel-cc:variantParameter>
      <actel-cc:variantParameter spirit:id="RTC_WAKEUP_CONFIG_OVERRIDE" spirit:name="RTC_WAKEUP_CONFIG_OVERRIDE" spirit:prompt="RTC_WAKEUP_CONFIG" actel-cc:choiceRef="" spirit:dataType="boolean" spirit:configGroups="4Cols:Allow Configuration Registers Override from Masters" spirit:resolve="user">1</actel-cc:variantParameter>
      <actel-cc:variantParameter spirit:id="MAC_CONFIG_OVERRIDE" spirit:name="MAC_CONFIG_OVERRIDE" spirit:prompt="MAC_CONFIG" actel-cc:choiceRef="" spirit:dataType="boolean" spirit:configGroups="4Cols:Allow Configuration Registers Override from Masters" spirit:resolve="user">1</actel-cc:variantParameter>
      <actel-cc:variantParameter spirit:id="MSSDDR_PLL_STATUS_LOW_OVERRIDE" spirit:name="MSSDDR_PLL_STATUS_LOW_OVERRIDE" spirit:prompt="MSSDDR_PLL_STATUS_LOW" actel-cc:choiceRef="" spirit:dataType="boolean" spirit:configGroups="4Cols:Allow Configuration Registers Override from Masters" spirit:resolve="user">1</actel-cc:variantParameter>
      <actel-cc:variantParameter spirit:id="MSSDDR_PLL_STATUS_HIGH_OVERRIDE" spirit:name="MSSDDR_PLL_STATUS_HIGH_OVERRIDE" spirit:prompt="MSSDDR_PLL_STATUS_HIGH" actel-cc:choiceRef="" spirit:dataType="boolean" spirit:configGroups="4Cols:Allow Configuration Registers Override from Masters" spirit:resolve="user">1</actel-cc:variantParameter>
      <actel-cc:variantParameter spirit:id="MSSDDR_FACC_CONFIG_1_OVERRIDE" spirit:name="MSSDDR_FACC_CONFIG_1_OVERRIDE" spirit:prompt="MSSDDR_FACC_CONFIG_1" actel-cc:choiceRef="" spirit:dataType="boolean" spirit:configGroups="4Cols:Allow Configuration Registers Override from Masters" spirit:resolve="user">1</actel-cc:variantParameter>
      <actel-cc:variantParameter spirit:id="MSSDDR_FACC_CONFIG_2_OVERRIDE" spirit:name="MSSDDR_FACC_CONFIG_2_OVERRIDE" spirit:prompt="MSSDDR_FACC_CONFIG_2" actel-cc:choiceRef="" spirit:dataType="boolean" spirit:configGroups="4Cols:Allow Configuration Registers Override from Masters" spirit:resolve="user">1</actel-cc:variantParameter>
      <actel-cc:variantParameter spirit:id="PLL_LOCK_EN_OVERRIDE" spirit:name="PLL_LOCK_EN_OVERRIDE" spirit:prompt="PLL_LOCK_EN" actel-cc:choiceRef="" spirit:dataType="boolean" spirit:configGroups="4Cols:Allow Configuration Registers Override from Masters" spirit:resolve="user">1</actel-cc:variantParameter>
      <actel-cc:variantParameter spirit:id="MSSDDR_CLK_CALIB_CONFIG_OVERRIDE" spirit:name="MSSDDR_CLK_CALIB_CONFIG_OVERRIDE" spirit:prompt="MSSDDR_CLK_CALIB_CONFIG" actel-cc:choiceRef="" spirit:dataType="boolean" spirit:configGroups="4Cols:Allow Configuration Registers Override from Masters" spirit:resolve="user">1</actel-cc:variantParameter>
      <actel-cc:variantParameter spirit:id="SOFTRESET_ENVM0_SOFTRESET_OVERRIDE" spirit:name="SOFTRESET_ENVM0_SOFTRESET_OVERRIDE" spirit:prompt="ENVM0_SOFTRESET" actel-cc:choiceRef="" spirit:dataType="boolean" spirit:configGroups="4Cols:Allow SOFTRESET Configuration Register Override from Masters" spirit:resolve="user">1</actel-cc:variantParameter>
      <actel-cc:variantParameter spirit:id="SOFTRESET_ENVM1_SOFTRESET_OVERRIDE" spirit:name="SOFTRESET_ENVM1_SOFTRESET_OVERRIDE" spirit:prompt="ENVM1_SOFTRESET" actel-cc:choiceRef="" spirit:dataType="boolean" spirit:configGroups="4Cols:Allow SOFTRESET Configuration Register Override from Masters" spirit:resolve="user">1</actel-cc:variantParameter>
      <actel-cc:variantParameter spirit:id="SOFTRESET_ESRAM0_SOFTRESET_OVERRIDE" spirit:name="SOFTRESET_ESRAM0_SOFTRESET_OVERRIDE" spirit:prompt="ESRAM0_SOFTRESET" actel-cc:choiceRef="" spirit:dataType="boolean" spirit:configGroups="4Cols:Allow SOFTRESET Configuration Register Override from Masters" spirit:resolve="user">1</actel-cc:variantParameter>
      <actel-cc:variantParameter spirit:id="SOFTRESET_ESRAM1_SOFTRESET_OVERRIDE" spirit:name="SOFTRESET_ESRAM1_SOFTRESET_OVERRIDE" spirit:prompt="ESRAM1_SOFTRESET" actel-cc:choiceRef="" spirit:dataType="boolean" spirit:configGroups="4Cols:Allow SOFTRESET Configuration Register Override from Masters" spirit:resolve="user">1</actel-cc:variantParameter>
      <actel-cc:variantParameter spirit:id="SOFTRESET_MAC_SOFTRESET_OVERRIDE" spirit:name="SOFTRESET_MAC_SOFTRESET_OVERRIDE" spirit:prompt="MAC_SOFTRESET" actel-cc:choiceRef="" spirit:dataType="boolean" spirit:configGroups="4Cols:Allow SOFTRESET Configuration Register Override from Masters" spirit:resolve="user">1</actel-cc:variantParameter>
      <actel-cc:variantParameter spirit:id="SOFTRESET_PDMA_SOFTRESET_OVERRIDE" spirit:name="SOFTRESET_PDMA_SOFTRESET_OVERRIDE" spirit:prompt="PDMA_SOFTRESET" actel-cc:choiceRef="" spirit:dataType="boolean" spirit:configGroups="4Cols:Allow SOFTRESET Configuration Register Override from Masters" spirit:resolve="user">1</actel-cc:variantParameter>
      <actel-cc:variantParameter spirit:id="SOFTRESET_TIMER_SOFTRESET_OVERRIDE" spirit:name="SOFTRESET_TIMER_SOFTRESET_OVERRIDE" spirit:prompt="TIMER_SOFTRESET" actel-cc:choiceRef="" spirit:dataType="boolean" spirit:configGroups="4Cols:Allow SOFTRESET Configuration Register Override from Masters" spirit:resolve="user">1</actel-cc:variantParameter>
      <actel-cc:variantParameter spirit:id="SOFTRESET_MMUART0_SOFTRESET_OVERRIDE" spirit:name="SOFTRESET_MMUART0_SOFTRESET_OVERRIDE" spirit:prompt="MMUART0_SOFTRESET" actel-cc:choiceRef="" spirit:dataType="boolean" spirit:configGroups="4Cols:Allow SOFTRESET Configuration Register Override from Masters" spirit:resolve="user">1</actel-cc:variantParameter>
      <actel-cc:variantParameter spirit:id="SOFTRESET_MMUART1_SOFTRESET_OVERRIDE" spirit:name="SOFTRESET_MMUART1_SOFTRESET_OVERRIDE" spirit:prompt="MMUART1_SOFTRESET" actel-cc:choiceRef="" spirit:dataType="boolean" spirit:configGroups="4Cols:Allow SOFTRESET Configuration Register Override from Masters" spirit:resolve="user">1</actel-cc:variantParameter>
      <actel-cc:variantParameter spirit:id="SOFTRESET_G4SPI0_SOFTRESET_OVERRIDE" spirit:name="SOFTRESET_G4SPI0_SOFTRESET_OVERRIDE" spirit:prompt="G4SPI0_SOFTRESET" actel-cc:choiceRef="" spirit:dataType="boolean" spirit:configGroups="4Cols:Allow SOFTRESET Configuration Register Override from Masters" spirit:resolve="user">1</actel-cc:variantParameter>
      <actel-cc:variantParameter spirit:id="SOFTRESET_G4SPI1_SOFTRESET_OVERRIDE" spirit:name="SOFTRESET_G4SPI1_SOFTRESET_OVERRIDE" spirit:prompt="G4SPI1_SOFTRESET" actel-cc:choiceRef="" spirit:dataType="boolean" spirit:configGroups="4Cols:Allow SOFTRESET Configuration Register Override from Masters" spirit:resolve="user">1</actel-cc:variantParameter>
      <actel-cc:variantParameter spirit:id="SOFTRESET_I2C0_SOFTRESET_OVERRIDE" spirit:name="SOFTRESET_I2C0_SOFTRESET_OVERRIDE" spirit:prompt="I2C0_SOFTRESET" actel-cc:choiceRef="" spirit:dataType="boolean" spirit:configGroups="4Cols:Allow SOFTRESET Configuration Register Override from Masters" spirit:resolve="user">1</actel-cc:variantParameter>
      <actel-cc:variantParameter spirit:id="SOFTRESET_I2C1_SOFTRESET_OVERRIDE" spirit:name="SOFTRESET_I2C1_SOFTRESET_OVERRIDE" spirit:prompt="I2C1_SOFTRESET" actel-cc:choiceRef="" spirit:dataType="boolean" spirit:configGroups="4Cols:Allow SOFTRESET Configuration Register Override from Masters" spirit:resolve="user">1</actel-cc:variantParameter>
      <actel-cc:variantParameter spirit:id="SOFTRESET_CAN_SOFTRESET_OVERRIDE" spirit:name="SOFTRESET_CAN_SOFTRESET_OVERRIDE" spirit:prompt="CAN_SOFTRESET" actel-cc:choiceRef="" spirit:dataType="boolean" spirit:configGroups="4Cols:Allow SOFTRESET Configuration Register Override from Masters" spirit:resolve="user">1</actel-cc:variantParameter>
      <actel-cc:variantParameter spirit:id="SOFTRESET_USB_SOFTRESET_OVERRIDE" spirit:name="SOFTRESET_USB_SOFTRESET_OVERRIDE" spirit:prompt="USB_SOFTRESET" actel-cc:choiceRef="" spirit:dataType="boolean" spirit:configGroups="4Cols:Allow SOFTRESET Configuration Register Override from Masters" spirit:resolve="user">1</actel-cc:variantParameter>
      <actel-cc:variantParameter spirit:id="SOFTRESET_COMBLK_SOFTRESET_OVERRIDE" spirit:name="SOFTRESET_COMBLK_SOFTRESET_OVERRIDE" spirit:prompt="COMBLK_SOFTRESET" actel-cc:choiceRef="" spirit:dataType="boolean" spirit:configGroups="4Cols:Allow SOFTRESET Configuration Register Override from Masters" spirit:resolve="user">1</actel-cc:variantParameter>
      <actel-cc:variantParameter spirit:id="SOFTRESET_FPGA_SOFTRESET_OVERRIDE" spirit:name="SOFTRESET_FPGA_SOFTRESET_OVERRIDE" spirit:prompt="FPGA_SOFTRESET" actel-cc:choiceRef="" spirit:dataType="boolean" spirit:configGroups="4Cols:Allow SOFTRESET Configuration Register Override from Masters" spirit:resolve="user">1</actel-cc:variantParameter>
      <actel-cc:variantParameter spirit:id="SOFTRESET_HPDMA_SOFTRESET_OVERRIDE" spirit:name="SOFTRESET_HPDMA_SOFTRESET_OVERRIDE" spirit:prompt="HPDMA_SOFTRESET" actel-cc:choiceRef="" spirit:dataType="boolean" spirit:configGroups="4Cols:Allow SOFTRESET Configuration Register Override from Masters" spirit:resolve="user">1</actel-cc:variantParameter>
      <actel-cc:variantParameter spirit:id="SOFTRESET_FIC32_0_SOFTRESET_OVERRIDE" spirit:name="SOFTRESET_FIC32_0_SOFTRESET_OVERRIDE" spirit:prompt="FIC32_0_SOFTRESET" actel-cc:choiceRef="" spirit:dataType="boolean" spirit:configGroups="4Cols:Allow SOFTRESET Configuration Register Override from Masters" spirit:resolve="user">1</actel-cc:variantParameter>
      <actel-cc:variantParameter spirit:id="SOFTRESET_FIC32_1_SOFTRESET_OVERRIDE" spirit:name="SOFTRESET_FIC32_1_SOFTRESET_OVERRIDE" spirit:prompt="FIC32_1_SOFTRESET" actel-cc:choiceRef="" spirit:dataType="boolean" spirit:configGroups="4Cols:Allow SOFTRESET Configuration Register Override from Masters" spirit:resolve="user">1</actel-cc:variantParameter>
      <actel-cc:variantParameter spirit:id="SOFTRESET_MSS_GPIO_SOFTRESET_OVERRIDE" spirit:name="SOFTRESET_MSS_GPIO_SOFTRESET_OVERRIDE" spirit:prompt="MSS_GPIO_SOFTRESET" actel-cc:choiceRef="" spirit:dataType="boolean" spirit:configGroups="4Cols:Allow SOFTRESET Configuration Register Override from Masters" spirit:resolve="user">1</actel-cc:variantParameter>
      <actel-cc:variantParameter spirit:id="SOFTRESET_MSS_GPOUT_7_0_SOFT_RESET_OVERRIDE" spirit:name="SOFTRESET_MSS_GPOUT_7_0_SOFT_RESET_OVERRIDE" spirit:prompt="MSS_GPOUT_7_0_SOFT_RESET" actel-cc:choiceRef="" spirit:dataType="boolean" spirit:configGroups="4Cols:Allow SOFTRESET Configuration Register Override from Masters" spirit:resolve="user">1</actel-cc:variantParameter>
      <actel-cc:variantParameter spirit:id="SOFTRESET_MSS_GPOUT_15_8_SOFT_RESET_OVERRIDE" spirit:name="SOFTRESET_MSS_GPOUT_15_8_SOFT_RESET_OVERRIDE" spirit:prompt="MSS_GPOUT_15_8_SOFT_RESET" actel-cc:choiceRef="" spirit:dataType="boolean" spirit:configGroups="4Cols:Allow SOFTRESET Configuration Register Override from Masters" spirit:resolve="user">1</actel-cc:variantParameter>
      <actel-cc:variantParameter spirit:id="SOFTRESET_MSS_GPOUT_23_16_SOFT_RESET_OVERRIDE" spirit:name="SOFTRESET_MSS_GPOUT_23_16_SOFT_RESET_OVERRIDE" spirit:prompt="MSS_GPOUT_23_16_SOFT_RESET" actel-cc:choiceRef="" spirit:dataType="boolean" spirit:configGroups="4Cols:Allow SOFTRESET Configuration Register Override from Masters" spirit:resolve="user">1</actel-cc:variantParameter>
      <actel-cc:variantParameter spirit:id="SOFTRESET_MSS_GPOUT_31_24_SOFT_RESET_OVERRIDE" spirit:name="SOFTRESET_MSS_GPOUT_31_24_SOFT_RESET_OVERRIDE" spirit:prompt="MSS_GPOUT_31_24_SOFT_RESET" actel-cc:choiceRef="" spirit:dataType="boolean" spirit:configGroups="4Cols:Allow SOFTRESET Configuration Register Override from Masters" spirit:resolve="user">1</actel-cc:variantParameter>
      <actel-cc:variantParameter spirit:id="SOFTRESET_MDDR_CTLR_SOFTRESET_OVERRIDE" spirit:name="SOFTRESET_MDDR_CTLR_SOFTRESET_OVERRIDE" spirit:prompt="MDDR_CTLR_SOFTRESET" actel-cc:choiceRef="" spirit:dataType="boolean" spirit:configGroups="4Cols:Allow SOFTRESET Configuration Register Override from Masters" spirit:resolve="user">1</actel-cc:variantParameter>
      <actel-cc:variantParameter spirit:id="SOFTRESET_MDDR_FIC64_SOFTRESET_OVERRIDE" spirit:name="SOFTRESET_MDDR_FIC64_SOFTRESET_OVERRIDE" spirit:prompt="MDDR_FIC64_SOFTRESET" actel-cc:choiceRef="" spirit:dataType="boolean" spirit:configGroups="4Cols:Allow SOFTRESET Configuration Register Override from Masters" spirit:resolve="user">1</actel-cc:variantParameter>
    </actel-cc:variantParameters>
    <actel-cc:script>Enable('FABRIC_MEMPROT_REGION_SIZE', Eq('FABRIC_MEMPROT_IS_USED', '1'));\
Enable('FABRIC_MEMPROT_BASE_ADDRESS', Eq('FABRIC_MEMPROT_IS_USED', '1'));\
Validate('Address must be a 32-bit hexadecimal number', IsHexOfWidth('FABRIC_MEMPROT_BASE_ADDRESS', '32'));\
</actel-cc:script></spirit:vendorExtensions>
  </spirit:hwModel>
  <spirit:componentGenerators>
    <spirit:componentGenerator>
      <spirit:name>pa4msssecurity</spirit:name>
      <spirit:generatorExe>file://{ACTEL_SW_DIR}/bin/pa4msssecurity.exe</spirit:generatorExe>
      <spirit:apiType>TGI</spirit:apiType>
      <spirit:group>Configurator,Win32</spirit:group>
    </spirit:componentGenerator>
    <spirit:componentGenerator>
      <spirit:name>pa4msssecurity_UNIX</spirit:name>
      <spirit:generatorExe>file://{ACTEL_SW_DIR}/bin/pa4msssecurity</spirit:generatorExe>
      <spirit:apiType>TGI</spirit:apiType>
      <spirit:group>Configurator,Unix</spirit:group>
    </spirit:componentGenerator>
  </spirit:componentGenerators>
  <spirit:choices>
    <spirit:choice>
      <spirit:name>Choice_FamilyValue</spirit:name>
      <spirit:enumeration spirit:text="SmartFusion2">19</spirit:enumeration>
    </spirit:choice>
    <spirit:choice>
      <spirit:name>FABRIC_MEMPROT_REGION_SIZE_CHOICES</spirit:name>
      <spirit:enumeration spirit:text="128B">128B</spirit:enumeration>
      <spirit:enumeration spirit:text="2KB">2KB</spirit:enumeration>
      <spirit:enumeration spirit:text="16KB">16KB</spirit:enumeration>
      <spirit:enumeration spirit:text="32KB">32KB</spirit:enumeration>
      <spirit:enumeration spirit:text="64KB">64KB</spirit:enumeration>
      <spirit:enumeration spirit:text="128KB">128KB</spirit:enumeration>
      <spirit:enumeration spirit:text="256KB">256KB</spirit:enumeration>
      <spirit:enumeration spirit:text="512KB">512KB</spirit:enumeration>
      <spirit:enumeration spirit:text="8MB">8MB</spirit:enumeration>
    </spirit:choice>
  </spirit:choices>
  <spirit:fileSets>
  </spirit:fileSets>
  <spirit:vendorExtensions>
    <actel-cc:displayName>MSS_SECURITY</actel-cc:displayName>
    <actel-cc:packageTimestamp>20130307092721</actel-cc:packageTimestamp>
    <actel-cc:type typeName="IP"/>
    <actel-cc:instantiateOnCreation value="false"/>
    <actel-cc:categories categoryName="OS" style="hidden">
      <actel-cc:category name="PC">
      </actel-cc:category>
      <actel-cc:category name="Linux">
      </actel-cc:category>
    </actel-cc:categories>
    <actel-cc:categories categoryName="min_libero_version" style="hidden">
      <actel-cc:category name="11.0.0">
      </actel-cc:category>
    </actel-cc:categories>
    <actel-cc:categories categoryName="display" style="hidden">
      <actel-cc:category name="hidden">
      </actel-cc:category>
    </actel-cc:categories>
    <actel-cc:categories categoryName="Product Family" style="checkbox">
      <actel-cc:category name="SmartFusion2">
      </actel-cc:category>
    </actel-cc:categories>
  </spirit:vendorExtensions>
</spirit:component>
